README.md
setup.py
example_censor.egg-info/PKG-INFO
example_censor.egg-info/SOURCES.txt
example_censor.egg-info/dependency_links.txt
example_censor.egg-info/top_level.txt
provider/__init__.py
provider/censor.py
provider/profanity_provider.py
provider/sub_package/__init__.py
provider/sub_package/example_module.py