Metadata-Version: 1.0
Name: example-censor
Version: 0.0.1
Summary: example description
Home-page: UNKNOWN
Author: example author
Author-email: UNKNOWN
License: UNKNOWN
Platform: UNKNOWN
